CouchbaseManager.py
robotframework_couchbasemanager-2.0.0.dist-info/LICENSE
robotframework_couchbasemanager-2.0.0.dist-info/METADATA
robotframework_couchbasemanager-2.0.0.dist-info/WHEEL
robotframework_couchbasemanager-2.0.0.dist-info/top_level.txt
robotframework_couchbasemanager-2.0.0.dist-info/RECORD
