Metadata-Version: 2.1
Name: robotframework-couchbasemanager
Version: 2.0.0
Summary: Robot Framework Library For Managing Couchbase Server.
Home-page: https://github.com/peterservice-rnd/robotframework-couchbasemanager
Author: JSC PETER-SERVICE
Author-email: mf_aist_all@billing.ru
License: Apache License 2.0
Keywords: testing testautomation robotframework autotest requests http couchbase
Platform: UNKNOWN
Classifier: Development Status :: 5 - Production/Stable
Classifier: Intended Audience :: Developers
Classifier: Topic :: Software Development :: Testing
Classifier: License :: OSI Approved :: Apache Software License
Classifier: Programming Language :: Python :: 3.5
Classifier: Programming Language :: Python :: 3.6
Classifier: Framework :: Robot Framework :: Library
Requires-Dist: requests
Requires-Dist: robotframework
